redisgraph_bulk_loader/__init__.py
redisgraph_bulk_loader/bulk_insert.py
redisgraph_bulk_loader/bulk_update.py
redisgraph_bulk_loader/config.py
redisgraph_bulk_loader/entity_file.py
redisgraph_bulk_loader/exceptions.py
redisgraph_bulk_loader/label.py
redisgraph_bulk_loader/query_buffer.py
redisgraph_bulk_loader/relation_type.py
redisgraph_bulk_loader-0.12.3.dist-info/WHEEL
redisgraph_bulk_loader-0.12.3.dist-info/LICENSE
redisgraph_bulk_loader-0.12.3.dist-info/entry_points.txt
redisgraph_bulk_loader-0.12.3.dist-info/METADATA
redisgraph_bulk_loader-0.12.3.dist-info/RECORD
