Metadata-Version: 2.1
Name: redisgraph-bulk-loader
Version: 0.12.3
Summary: RedisGraph Bulk Import Tool
License: BSD-3-Clause
Keywords: Redis Graph Extension
Author: Redis Inc
Author-email: oss@redis.com
Requires-Python: >=3.7.0
Classifier: Development Status :: 5 - Production/Stable
Classifier: Intended Audience :: Developers
Classifier: License :: OSI Approved :: BSD License
Classifier: Programming Language :: Python
Classifier: Programming Language :: Python :: 3
Classifier: Programming Language :: Python :: 3.7
Classifier: Programming Language :: Python :: 3.8
Classifier: Programming Language :: Python :: 3.9
Classifier: Programming Language :: Python :: 3.10
Classifier: Programming Language :: Python :: 3.11
Classifier: Programming Language :: Python :: 3.10
Classifier: Programming Language :: Python :: 3.11
Classifier: Programming Language :: Python :: 3.7
Classifier: Programming Language :: Python :: 3.8
Classifier: Programming Language :: Python :: 3.9
Classifier: Topic :: Database
Requires-Dist: click (>=8.0.1,<9.0.0)
Requires-Dist: pathos (>=0.2.8,<0.3.0)
Requires-Dist: redis (>=4.5.1,<5.0.0)
Project-URL: repository, https://github.com/RedisGraph/redisgraph-bulk-loader
Project-URL: url, https://redisgraph.io
